[
  {
    "linha": 1,
    "tipo_vertice": "num",
    "tipo_inferido": "int",
    "valor": 5,
    "filhos": []
  },
  {
    "linha": 2,
    "tipo_vertice": "num",
    "tipo_inferido": "int",
    "valor": 10,
    "filhos": []
  },
  {
    "linha": 3,
    "tipo_vertice": "plus",
    "tipo_inferido": "int",
    "valor": "+",
    "filhos": [
      {
        "tipo_vertice": "num",
        "tipo_inferido": "int",
        "valor": 5,
        "filhos": []
      },
      {
        "tipo_vertice": "num",
        "tipo_inferido": "int",
        "valor": 3,
        "filhos": []
      }
    ]
  },
  {
    "linha": 4,
    "tipo_vertice": "mult",
    "tipo_inferido": "real",
    "valor": "*",
    "filhos": [
      {
        "tipo_vertice": "num",
        "tipo_inferido": "int",
        "valor": 10,
        "filhos": []
      },
      {
        "tipo_vertice": "num",
        "tipo_inferido": "real",
        "valor": 2.5,
        "filhos": []
      }
    ]
  },
  {
    "linha": 5,
    "tipo_vertice": "div_real",
    "tipo_inferido": "real",
    "valor": "|",
    "filhos": [
      {
        "tipo_vertice": "num",
        "tipo_inferido": "int",
        "valor": 100,
        "filhos": []
      },
      {
        "tipo_vertice": "num",
        "tipo_inferido": "real",
        "valor": 2.52,
        "filhos": []
      }
    ]
  },
  {
    "linha": 6,
    "tipo_vertice": "res",
    "tipo_inferido": "real",
    "valor": "RES",
    "filhos": [
      {
        "tipo_vertice": "num",
        "tipo_inferido": "int",
        "valor": 1,
        "filhos": []
      }
    ]
  },
  {
    "linha": 7,
    "tipo_vertice": "res",
    "tipo_inferido": "int",
    "valor": "RES",
    "filhos": [
      {
        "tipo_vertice": "num",
        "tipo_inferido": "int",
        "valor": 4,
        "filhos": []
      }
    ]
  }
]